pykustomize/__init__.py
pykustomize/_ffi.py
pykustomize/build.py
pykustomize/exceptions.py
pykustomize/_lib/linux-amd64/libpykustomize.h
pykustomize/_lib/linux-amd64/libpykustomize.so
pykustomize-0.1.1.data/data/pykustomize/_lib/linux-amd64/libpykustomize.h
pykustomize-0.1.1.data/data/pykustomize/_lib/linux-amd64/libpykustomize.so
pykustomize-0.1.1.dist-info/METADATA
pykustomize-0.1.1.dist-info/WHEEL
pykustomize-0.1.1.dist-info/licenses/LICENSE
pykustomize-0.1.1.dist-info/RECORD
