Metadata-Version: 2.4
Name: pykustomize
Version: 0.1.1
Summary: Python bindings for Kustomize - Kubernetes configuration customization
Project-URL: Homepage, https://github.com/vantagecompute/pykustomize
Project-URL: Repository, https://github.com/vantagecompute/pykustomize
Project-URL: Documentation, https://github.com/vantagecompute/pykustomize#readme
Project-URL: Issues, https://github.com/vantagecompute/pykustomize/issues
Author-email: Vantage Compute <support@vantagecompute.io>
License-Expression: Apache-2.0
License-File: LICENSE
Keywords: configuration,devops,k8s,kubernetes,kustomize,yaml
Classifier: Development Status :: 4 - Beta
Classifier: Intended Audience :: Developers
Classifier: License :: OSI Approved :: Apache Software License
Classifier: Operating System :: MacOS :: MacOS X
Classifier: Operating System :: Microsoft :: Windows
Classifier: Operating System :: POSIX :: Linux
Classifier: Programming Language :: Go
Classifier: Programming Language :: Python :: 3
Classifier: Programming Language :: Python :: 3.14
Classifier: Topic :: Software Development :: Libraries :: Python Modules
Classifier: Topic :: System :: Systems Administration
Classifier: Typing :: Typed
Requires-Python: >=3.14
Requires-Dist: cffi>=1.16.0
Provides-Extra: dev
Requires-Dist: pyright>=1.1.350; extra == 'dev'
Requires-Dist: pytest-asyncio>=0.23.0; extra == 'dev'
Requires-Dist: pytest-cov>=4.1.0; extra == 'dev'
Requires-Dist: pytest>=8.0.0; extra == 'dev'
Requires-Dist: ruff>=0.3.0; extra == 'dev'
